RW/__init__.py
rw_workspace_utils_keywords-0.0.2.dist-info/LICENSE
rw_workspace_utils_keywords-0.0.2.dist-info/METADATA
rw_workspace_utils_keywords-0.0.2.dist-info/WHEEL
rw_workspace_utils_keywords-0.0.2.dist-info/top_level.txt
rw_workspace_utils_keywords-0.0.2.dist-info/RECORD
